<?xml version="1.0" encoding="utf-8"?>
<odoo>
    <data noupdate="1">
        <record id="communication_1" model="crm.extra.data">
            <field name="name">Inbound CS Individual</field>
        </record>
        <record id="call_type_1" model="crm.extra.data">
            <field name="name">Info.</field>
            <field name="parent_id" ref="communication_1"/>
        </record>
        <record id="reason_1" model="crm.extra.data">
            <field name="name">Account details</field>
            <field name="parent_id" ref="call_type_1"/>
        </record>
        <record id="reason_2" model="crm.extra.data">
            <field name="name">Merchant</field>
            <field name="parent_id" ref="call_type_1"/>
        </record>
        <record id="reason_3" model="crm.extra.data">
            <field name="name">Payment methods</field>
            <field name="parent_id" ref="call_type_1"/>
        </record>
        <record id="reason_4" model="crm.extra.data">
            <field name="name">Promotions</field>
            <field name="parent_id" ref="call_type_1"/>
        </record>
        <record id="reason_5" model="crm.extra.data">
            <field name="name">Campaigns</field>
            <field name="parent_id" ref="call_type_1"/>
        </record>
        <record id="reason_6" model="crm.extra.data">
            <field name="name">Complaint</field>
            <field name="parent_id" ref="call_type_1"/>
        </record>
        <record id="reason_7" model="crm.extra.data">
            <field name="name">Account status</field>
            <field name="parent_id" ref="call_type_1"/>
        </record>
        <record id="reason_8" model="crm.extra.data">
            <field name="name">Special request</field>
            <field name="parent_id" ref="call_type_1"/>
        </record>
        <record id="reason_9" model="crm.extra.data">
            <field name="name">Product</field>
            <field name="parent_id" ref="call_type_1"/>
        </record>

        <record id="concern_1" model="crm.extra.data">
            <field name="name">Registration</field>
            <field name="parent_id" ref="reason_1"/>
        </record>
        <record id="concern_2" model="crm.extra.data">
            <field name="name">Rejection reason</field>
            <field name="parent_id" ref="reason_1"/>
        </record>
        <record id="concern_3" model="crm.extra.data">
            <field name="name">Purchasing Tech. issue</field>
            <field name="parent_id" ref="reason_1"/>
        </record>
        <record id="concern_4" model="crm.extra.data">
            <field name="name">Limit</field>
            <field name="parent_id" ref="reason_1"/>
        </record>

        <record id="call_type_2" model="crm.extra.data">
            <field name="name">Request</field>
            <field name="parent_id" ref="communication_1"/>
        </record>
        <record id="call_type_3" model="crm.extra.data">
            <field name="name">Complain</field>
            <field name="parent_id" ref="communication_1"/>
        </record>
        <record id="communication_2" model="crm.extra.data">
            <field name="name">Inbound CS Merchant</field>
        </record>
        <record id="communication_3" model="crm.extra.data">
            <field name="name">Outbound CS Individual</field>
        </record>
        <record id="communication_4" model="crm.extra.data">
            <field name="name">Outbound CS Merchant</field>
        </record>
        <record id="communication_5" model="crm.extra.data">
            <field name="name">Outbound app support</field>
        </record>
        <record id="communication_6" model="crm.extra.data">
            <field name="name">Inbound client’s App support</field>
        </record>
        <record id="communication_7" model="crm.extra.data">
            <field name="name">Inbound merchant’s App support</field>
        </record>
    </data>
</odoo>

